conveyance/__init__.py
conveyance/example.py
conveyance-0.0.0.dist-info/LICENSE
conveyance-0.0.0.dist-info/METADATA
conveyance-0.0.0.dist-info/WHEEL
conveyance-0.0.0.dist-info/top_level.txt
conveyance-0.0.0.dist-info/RECORD
