Metadata-Version: 2.1
Name: conveyance
Version: 0.0.0
Summary: Python library for conveyor design
Home-page: https://github.com/ScottMcCormack/conveyance
Author: Scott McCormack
Author-email: scott.mccormack@quenda.io
License: UNKNOWN
Project-URL: Bug Tracker, https://github.com/ScottMcCormack/conveyance/issues
Platform: UNKNOWN
Classifier: Programming Language :: Python :: 3
Classifier: License :: OSI Approved :: GNU General Public License v3 (GPLv3)
Classifier: Operating System :: OS Independent
Requires-Python: >=3.6
License-File: LICENSE
